{"componentName": "Chart", "config": {"base": {"grid": {"left": 10, "right": 0, "top": 36, "bottom": 0, "containLabel": true}, "legend": {"data": ["需要実績", "需要予想", "供給実績", "供給予想"]}, "xAxis": {"type": "category", "data": ["0:00", "1:00", "2:00", "3:00", "4:00", "5:00", "6:00", "7:00", "8:00", "9:00", "10:00", "11:00", "12:00", "13:00", "14:00", "15:00", "16:00", "17:00", "18:00", "19:00", "20:00", "21:00", "22:00", "23:00"]}, "yAxis": {"type": "value"}, "series": [{"data": [null, null, null, null, null, null, null, null, null, null, null, null, null, null, null, null, null, null, null, null, null, null, null, null], "name": "需要実績", "type": "bar", "stack": "total"}, {"data": [3520, 3266, 3128, 3057, 3048, 3119, 3366, 3933, 4735, 5303, 5512, 5695, 5686, 5785, 5795, 5748, 5685, 5308, 5150, 5015, 4716, 4451, 4212, 3874], "name": "需要予想", "type": "bar", "stack": "total"}, {"data": [null, null, null, null, null, null, null, null, null, null, null, null, null, null, null, null, null, null, null, null, null, null, null, null], "name": "供給実績", "type": "line", "step": "middle", "lineStyle": {"width": 3}}, {"data": [4124, 4098, 4046, 3996, 3992, 4049, 4291, 4622, 5075, 5575, 5790, 5992, 5973, 6083, 6098, 6040, 5964, 5584, 5417, 5276, 4972, 4694, 4423, 4136], "name": "供給予想", "type": "line", "step": "middle", "lineStyle": {"width": 3}}]}, "light": {"legend": {"textStyle": {"color": "#666666"}}, "xAxis": {"type": "category", "axisLine": {"onZero": true, "lineStyle": {"color": "#AEAEAE"}}}, "yAxis": {"type": "value", "axisLine": {"lineStyle": {"color": "#AEAEAE"}}, "splitLine": {"lineStyle": {"color": "#AEAEAE", "width": 0.5}}}, "color": ["#a3bfcc", "#1d78a3", "#dbcfaf", "#ebb736"]}, "dark": {"legend": {"textStyle": {"color": "#eeeeee"}}, "xAxis": {"axisLine": {"onZero": false, "lineStyle": {"color": "#E5E5E5"}}}, "yAxis": {"type": "value", "axisLine": {"lineStyle": {"color": "#E5E5E5"}}, "splitLine": {"lineStyle": {"color": "#E5E5E5", "width": 0.5}}}, "color": ["#9babaa", "#04d4c6", "#d4d0b4", "#f2da3f"]}}}