{"componentName": "Chart", "config": {"base": {"grid": {"left": 10, "right": 0, "top": 58, "bottom": 0, "containLabel": true}, "legend": {"data": ["需要実績", "予想需要", "供給力実績", "予想供給力"]}, "xAxis": {"type": "category", "data": ["0:00", "1:00", "2:00", "3:00", "4:00", "5:00", "6:00", "7:00", "8:00", "9:00", "10:00", "11:00", "12:00", "13:00", "14:00", "15:00", "16:00", "17:00", "18:00", "19:00", "20:00", "21:00", "22:00", "23:00"]}, "yAxis": {"type": "value"}, "series": [{"data": [2518, 2395, 2351, 2365, 2384, 2394, 2439, 2599, 2877, 3081, 3272, 3349, 3331, 3278, 3177, 3107, 3116, 3214, 3261, null, null, null, null, null], "name": "需要実績", "type": "bar", "stack": "total"}, {"data": [null, null, null, null, null, null, null, null, null, null, null, null, null, null, null, null, null, null, null, 3133, 3020, 2855, 2723, 2580], "name": "予想需要", "type": "bar", "stack": "total"}, {"data": [3368, 2902, 2887, 2866, 2841, 2887, 2834, 3059, 3386, 3708, 3896, 4009, 3987, 4089, 4145, 4157, 4177, 4104, 4262, null, null, null, null, null], "name": "供給力実績", "type": "line", "step": "middle", "lineStyle": {"width": 3}}, {"data": [null, null, null, null, null, null, null, null, null, null, null, null, null, null, null, null, null, null, null, 4205, 4156, 4123, 3972, 3637], "name": "予想供給力", "type": "line", "step": "middle", "lineStyle": {"width": 3}}]}, "light": {"legend": {"textStyle": {"color": "#666666"}}, "xAxis": {"type": "category", "axisLine": {"onZero": true, "lineStyle": {"color": "#AEAEAE"}}}, "yAxis": {"type": "value", "axisLine": {"lineStyle": {"color": "#AEAEAE"}}, "axisLabel": {"formatter": "{value}万kW"}, "splitLine": {"lineStyle": {"color": "#AEAEAE", "width": 0.5}}}, "color": ["#a3bfcc", "#1d78a3", "#dbcfaf", "#ebb736"]}, "dark": {"legend": {"textStyle": {"color": "#eeeeee"}}, "xAxis": {"axisLine": {"onZero": false, "lineStyle": {"color": "#E5E5E5"}}}, "yAxis": {"type": "value", "axisLine": {"lineStyle": {"color": "#E5E5E5"}}, "axisLabel": {"formatter": "{value}万kW"}, "splitLine": {"lineStyle": {"color": "#E5E5E5", "width": 0.5}}}, "color": ["#9babaa", "#04d4c6", "#d4d0b4", "#f2da3f"]}}}