{"componentName": "Chart", "config": {"base": {"grid": {"left": 10, "right": 0, "top": 36, "bottom": 0, "containLabel": true}, "legend": {"data": ["需要実績", "需要予想", "供給実績", "供給予想"]}, "xAxis": {"type": "category", "data": ["0:00", "1:00", "2:00", "3:00", "4:00", "5:00", "6:00", "7:00", "8:00", "9:00", "10:00", "11:00", "12:00", "13:00", "14:00", "15:00", "16:00", "17:00", "18:00", "19:00", "20:00", "21:00", "22:00", "23:00"]}, "yAxis": {"type": "value"}, "series": [{"data": [3412, 3156, 3043, 3004, 3001, 3036, 3269, 3824, null, null, null, null, null, null, null, null, null, null, null, null, null, null, null, null], "name": "需要実績", "type": "bar", "stack": "total"}, {"data": [null, null, null, null, null, null, null, null, 4626, 5211, 5451, 5645, 5654, 5817, 5879, 5833, 5730, 5363, 5188, 5004, 4650, 4374, 4113, 3781], "name": "需要予想", "type": "bar", "stack": "total"}, {"data": [4029, 3998, 3952, 3922, 3921, 3963, 4228, 4603, null, null, null, null, null, null, null, null, null, null, null, null, null, null, null, null], "name": "供給実績", "type": "line", "step": "middle", "lineStyle": {"width": 3}}, {"data": [null, null, null, null, null, null, null, null, 5106, 5618, 5877, 6087, 6097, 6272, 6323, 6152, 5915, 5682, 5530, 5374, 5012, 4713, 4431, 4170], "name": "供給予想", "type": "line", "step": "middle", "lineStyle": {"width": 3}}]}, "light": {"legend": {"textStyle": {"color": "#666666"}}, "xAxis": {"type": "category", "axisLine": {"onZero": true, "lineStyle": {"color": "#AEAEAE"}}}, "yAxis": {"type": "value", "axisLine": {"lineStyle": {"color": "#AEAEAE"}}, "splitLine": {"lineStyle": {"color": "#AEAEAE", "width": 0.5}}}, "color": ["#a3bfcc", "#1d78a3", "#dbcfaf", "#ebb736"]}, "dark": {"legend": {"textStyle": {"color": "#eeeeee"}}, "xAxis": {"axisLine": {"onZero": false, "lineStyle": {"color": "#E5E5E5"}}}, "yAxis": {"type": "value", "axisLine": {"lineStyle": {"color": "#E5E5E5"}}, "splitLine": {"lineStyle": {"color": "#E5E5E5", "width": 0.5}}}, "color": ["#9babaa", "#04d4c6", "#d4d0b4", "#f2da3f"]}}}