{"componentName": "Chart", "config": {"base": {"grid": {"left": 10, "right": 0, "top": 58, "bottom": 0, "containLabel": true}, "legend": {"data": ["需要実績", "予想需要", "供給力実績", "予想供給力"]}, "xAxis": {"type": "category", "data": ["0:00", "1:00", "2:00", "3:00", "4:00", "5:00", "6:00", "7:00", "8:00", "9:00", "10:00", "11:00", "12:00", "13:00", "14:00", "15:00", "16:00", "17:00", "18:00", "19:00", "20:00", "21:00", "22:00", "23:00"]}, "yAxis": {"type": "value"}, "series": [{"data": [2373, null, null, null, null, null, null, null, null, null, null, null, null, null, null, null, null, null, null, null, null, null, null, null], "name": "需要実績", "type": "bar", "stack": "total"}, {"data": [null, 2307, 2321, 2356, 2424, 2586, 2812, 3011, 3256, 3376, 3378, 3347, 3185, 3241, 3177, 3127, 3162, 3116, 3300, 3213, 3102, 2962, 2818, 2645], "name": "予想需要", "type": "bar", "stack": "total"}, {"data": [2923, null, null, null, null, null, null, null, null, null, null, null, null, null, null, null, null, null, null, null, null, null, null, null], "name": "供給力実績", "type": "line", "step": "middle", "lineStyle": {"width": 3}}, {"data": [null, 2849, 2873, 2917, 3000, 3201, 3481, 3726, 4030, 4179, 4181, 4146, 3944, 4012, 3932, 3870, 3914, 3857, 4085, 3977, 3839, 3666, 3488, 3274], "name": "予想供給力", "type": "line", "step": "middle", "lineStyle": {"width": 3}}]}, "light": {"legend": {"textStyle": {"color": "#666666"}}, "xAxis": {"type": "category", "axisLine": {"onZero": true, "lineStyle": {"color": "#AEAEAE"}}}, "yAxis": {"type": "value", "axisLine": {"lineStyle": {"color": "#AEAEAE"}}, "axisLabel": {"formatter": "{value}万kW"}, "splitLine": {"lineStyle": {"color": "#AEAEAE", "width": 0.5}}}, "color": ["#a3bfcc", "#1d78a3", "#dbcfaf", "#ebb736"]}, "dark": {"legend": {"textStyle": {"color": "#eeeeee"}}, "xAxis": {"axisLine": {"onZero": false, "lineStyle": {"color": "#E5E5E5"}}}, "yAxis": {"type": "value", "axisLine": {"lineStyle": {"color": "#E5E5E5"}}, "axisLabel": {"formatter": "{value}万kW"}, "splitLine": {"lineStyle": {"color": "#E5E5E5", "width": 0.5}}}, "color": ["#9babaa", "#04d4c6", "#d4d0b4", "#f2da3f"]}}}